haystack_integrations/components/preprocessors/py.typed
haystack_integrations/components/preprocessors/hanlp/__init__.py
haystack_integrations/components/preprocessors/hanlp/chinese_document_splitter.py
hanlp_haystack-2.1.0.dist-info/METADATA
hanlp_haystack-2.1.0.dist-info/WHEEL
hanlp_haystack-2.1.0.dist-info/licenses/LICENSE.txt
hanlp_haystack-2.1.0.dist-info/RECORD
